revealhashed/__init__.py
revealhashed/__main__.py
revealhashed/core.py
revealhashed/imports/__init__.py
revealhashed/imports/ntdsutil.py
revealhashed-0.2.1.dist-info/licenses/LICENSE
revealhashed-0.2.1.dist-info/METADATA
revealhashed-0.2.1.dist-info/WHEEL
revealhashed-0.2.1.dist-info/entry_points.txt
revealhashed-0.2.1.dist-info/top_level.txt
revealhashed-0.2.1.dist-info/RECORD
