Metadata-Version: 2.4
Name: revealhashed
Version: 0.2.1
Summary: Dump or analyze existing NTDS data, crack NT hashes with hashcat and match them to their corresponding user accounts.
Author-email: aslan emre aslan <emre@zurrak.com>
License: MIT
Requires-Python: >=3.7
License-File: LICENSE
Requires-Dist: impacket
Requires-Dist: neo4j
Dynamic: license-file
